StochasticGhost/StochasticGhost.py
StochasticGhost/__init__.py
StochasticGhost-0.2.1.dist-info/LICENSE
StochasticGhost-0.2.1.dist-info/METADATA
StochasticGhost-0.2.1.dist-info/WHEEL
StochasticGhost-0.2.1.dist-info/top_level.txt
StochasticGhost-0.2.1.dist-info/RECORD
