Metadata-Version: 2.1
Name: StochasticGhost
Version: 0.2.1
Summary: Empirical Risk minimization with constraints
Author: Vyacheslav Kungrutsev
Author-email: kunguvya@fel.cvut.cz
Requires-Python: ==3.10.*
License-File: LICENSE
Requires-Dist: setuptools
Requires-Dist: numpy
Requires-Dist: pot ==0.9.3
Requires-Dist: argparse
Requires-Dist: scipy ==1.11.4
Requires-Dist: qpsolvers ==4.2.0
Requires-Dist: scikit-learn ==1.3.0
Requires-Dist: matplotlib
Requires-Dist: autoray ==0.6.7
